{
  "name": "FxSpriteRotShapeNode",
  "properties": 
  [
    {
      "name": "unknownVector0",
      "type": "Vector4"
    },
    {
      "name": "unknownUint0",
      "type": "uint32"
    },
    {
      "name": "unknownFloat0",
      "type": "float"
    },
    {
      "name": "unknownFloat1",
      "type": "float"
    },
    {
      "name": "unknownBool0",
      "type": "bool"
    },
    {
      "name": "unknownBool1",
      "type": "bool"
    },
    {
      "name": "unknownBool2",
      "type": "bool"
    },
    {
      "name": "unknownVector1",
      "type": "Vector4"
    },
    {
      "name": "unknownVector2",
      "type": "Vector4"
    },
    {
      "name": "unknownUint3",
      "type": "uint32"
    },
    {
      "name": "unknownBool3",
      "type": "bool"
    },
    {
      "name": "unknownBool4",
      "type": "bool"
    },
    {
      "name": "unknownUint4",
      "type": "uint32"
    },
    {
      "name": "unknownUint5",
      "type": "uint32"
    }
  ]
}